{"name":"Anna Corliss Maggio Williams","Address_Line_1":"12761 Highway 90","Address_Line_2":"Suite A","City":"Grand Bay","State_Code":"AL","Zip_Code":"36541","Phone":" (251) 865-3665","Fax":" (251) 865-3650","Firm_Name":"","Firm_Website":"https://www.gulfcoastattorneys.com/","Law_School":"Jones School of Law","Law_School_Graduation_Year":"1977","Law_School_Degree":"JD - Juris Doctor","Bar_Admission":"Occupational License - Authorized to Practice","Bar_Admission_Year":"1978","First_Year_Admitted_To_Practice":"2013 - Present","Practice_Area_1":"Family","Practice_Area_2":"Real estate","Practice_Area_3":"Estate planning","Practice_Area_4":"Personal injury","Practice_Area_5":"Probate"}