{"name":"Alan Cameron Christian","Address_Line_1":"8 Drury Ln","Address_Line_2":"","City":"Mobile","State_Code":"AL","Zip_Code":"36608-2309","Phone":" (866) 732-3267","Fax":" (251) 680-2687","Firm_Name":"","Firm_Website":"www.johnstoneadams.com","Law_School":"University of Alabama","Law_School_Graduation_Year":"1977","Law_School_Degree":"BA - Bachelor of Arts","Bar_Admission":"Occupational License - Authorized to Practice","Bar_Admission_Year":"1980","First_Year_Admitted_To_Practice":"","Practice_Area_1":"Environmental and natural resources","Practice_Area_2":"Oil and gas","Practice_Area_3":"Banking","Practice_Area_4":"Admiralty and maritime","Practice_Area_5":""}