{"name":"Bryan Mcdaniel Taylor","Address_Line_1":"600 Dexter Ave Ste N 203","Address_Line_2":"","City":"Montgomery","State_Code":"AL","Zip_Code":"36130-3024","Phone":" (334) 242-7120","Fax":"","Firm_Name":"","Firm_Website":"www.govenor.alabama.gov","Law_School":"University of Texas School of Law","Law_School_Graduation_Year":"2001","Law_School_Degree":"Doctor of Jurisprudence/Juris Doctor (J.D.)","Bar_Admission":"Occupational License - Authorized to Practice","Bar_Admission_Year":"2006","First_Year_Admitted_To_Practice":"","Practice_Area_1":"Appeals","Practice_Area_2":"Military law","Practice_Area_3":"Commercial real estate","Practice_Area_4":"Government","Practice_Area_5":"Ethics and professional responsibility"}