{"name":"Katherine Anderson Harbison","Address_Line_1":"501 Riverchase Pkwy E Ste 100","Address_Line_2":"","City":"Hoover","State_Code":"AL","Zip_Code":"35244-1834","Phone":" (205) 716-3010","Fax":" (205) 716-3000","Firm_Name":"","Firm_Website":"http://www.gtandslaw.com/9-2/katherine-kip-harbison/","Law_School":"University of Alabama School of Law","Law_School_Graduation_Year":"1998","Law_School_Degree":"JD - Juris Doctor","Bar_Admission":"Occupational License - Authorized to Practice","Bar_Admission_Year":"1998","First_Year_Admitted_To_Practice":"","Practice_Area_1":"Administrative law","Practice_Area_2":"Tax","Practice_Area_3":"Class action","Practice_Area_4":"","Practice_Area_5":""}