{"name":"Sonya Christine Edwards","Address_Line_1":"121 Edenton St","Address_Line_2":"","City":"Birmingham","State_Code":"AL","Zip_Code":"35242-5260","Phone":"","Fax":"","Firm_Name":"","Firm_Website":"www.haynes-haynes.com","Law_School":"Birmingham-Southern College","Law_School_Graduation_Year":"2002","Law_School_Degree":"B.S.,","Bar_Admission":"Occupational License - Authorized to Practice","Bar_Admission_Year":"2005","First_Year_Admitted_To_Practice":"","Practice_Area_1":"Class action","Practice_Area_2":"Criminal defense","Practice_Area_3":"Arbitration","Practice_Area_4":"General practice","Practice_Area_5":"Litigation"}